nicegui_tabulator/__init__.py
nicegui_tabulator/version.py
nicegui_tabulator/core/dependencies.py
nicegui_tabulator/core/events.py
nicegui_tabulator/core/tabulator.js
nicegui_tabulator/core/tabulator.py
nicegui_tabulator/core/themes.py
nicegui_tabulator/core/types.py
nicegui_tabulator/core/utils.py
nicegui_tabulator/core/libs/tabulator.min.css
nicegui_tabulator/core/libs/tabulator.min.js
nicegui_tabulator/core/libs/tabulator_bootstrap3.min.css
nicegui_tabulator/core/libs/tabulator_bootstrap4.min.css
nicegui_tabulator/core/libs/tabulator_bootstrap5.min.css
nicegui_tabulator/core/libs/tabulator_bulma.min.css
nicegui_tabulator/core/libs/tabulator_materialize.min.css
nicegui_tabulator/core/libs/tabulator_midnight.min.css
nicegui_tabulator/core/libs/tabulator_modern.min.css
nicegui_tabulator/core/libs/tabulator_semanticui.min.css
nicegui_tabulator/core/libs/tabulator_simple.min.css
nicegui_tabulator/core/libs/tabulator_site.min.css
nicegui_tabulator/core/libs/tabulator_site_dark.min.css
nicegui_tabulator-0.2.3.dist-info/METADATA
nicegui_tabulator-0.2.3.dist-info/WHEEL
nicegui_tabulator-0.2.3.dist-info/licenses/LICENSE
nicegui_tabulator-0.2.3.dist-info/RECORD
