Metadata-Version: 2.4
Name: nicegui-tabulator
Version: 0.2.3
Summary: This is a Python package that provides a simple way to create tables using the Tabulator library. It is built on top of the NiceGUI library.
Author-email: CrystalWindSnake <568166495@qq.com>
License-Expression: MIT
License-File: LICENSE
Keywords: NiceGUI,Tabulator,gui,table,ui,web
Requires-Python: >=3.9
Requires-Dist: nicegui~=2.0
